pydeepleb/__init__.py
pydeepleb/avto.py
pydeepleb/init.py
pydeepleb-0.0.1.dist-info/METADATA
pydeepleb-0.0.1.dist-info/WHEEL
pydeepleb-0.0.1.dist-info/top_level.txt
pydeepleb-0.0.1.dist-info/RECORD
