Metadata-Version: 2.1
Name: pydeepleb
Version: 0.0.1
Summary: This is the simplest module for quick work with files.
Home-page: https://www.youtube.com/
Author: garik-g
Author-email: example@gmail.com
Project-URL: GitHub, https://www.youtube.com/
Keywords: files speedfiles
Classifier: Programming Language :: Python :: 3.11
Classifier: License :: OSI Approved :: MIT License
Classifier: Operating System :: OS Independent
Requires-Python: >=3.6
Requires-Dist: requests >=2.25.1
